Metadata-Version: 1.0
Name: peels
Version: 0.0.0
Summary: Pythonic byte manipulation parsing
Home-page: UNKNOWN
Author: Nathan Zilora
Author-email: zwork101@gmail.com
License: UNKNOWN
Keywords: bytes manipulation parsing pythonic
Platform: UNKNOWN
